CHANGELOG.txt
LICENSE.txt
MANIFEST.in
README.rst
requirements.txt
setup.cfg
setup.py
django_mininews.egg-info/PKG-INFO
django_mininews.egg-info/SOURCES.txt
django_mininews.egg-info/dependency_links.txt
django_mininews.egg-info/requires.txt
django_mininews.egg-info/top_level.txt
mininews/__init__.py
mininews/admin.py
mininews/managers.py
mininews/models.py
mininews/sitemaps.py
mininews/views.py
scripts/__init__.py
scripts/releaser_hooks.py